runtime_final/__init__.py
runtime_final/__init__.pyi
runtime_final/py.typed
amulet_runtime_final-1.1.2.dist-info/LICENSE
amulet_runtime_final-1.1.2.dist-info/METADATA
amulet_runtime_final-1.1.2.dist-info/WHEEL
amulet_runtime_final-1.1.2.dist-info/top_level.txt
amulet_runtime_final-1.1.2.dist-info/RECORD
